<graph id="testcase">
	<version>1.0</version>

	<node id="ICOL">
		<operator>IcolMeris</operator>
		<sources>
		        <sourceProduct>${sourceProduct}</sourceProduct>
		</sources>
		<parameters>
			<useUserCtp>true</useUserCtp>
			<icolAerosolForWater>true</icolAerosolForWater>
			<icolAerosolCase2>true</icolAerosolCase2>
			<openclConvolution>false</openclConvolution>
		</parameters>
	</node>

<!--<node id="AC">
  <operator>Meris.GlintCorrection</operator>
  <sources>
    <merisProduct>RC</merisProduct>
  </sources>
  <parameters>
    <useFlint>false</useFlint>
  </parameters>
</node>
-->

<!--
	<node id="cloudscreening">
		<operator>idepix.ComputeChain</operator>
		<sources>
			<source>preprocessNode1</source>
		</sources>
		<parameters>
			<algorithm>GlobAlbedo</algorithm>			
			<pressureOutputPbaro>true</pressureOutputPbaro>
			<pressurePbaroGetasse>true</pressurePbaroGetasse>
			<pressureOutputPsurfFub>true</pressureOutputPsurfFub>
			<pressureFubTropicalAtmosphere>true</pressureFubTropicalAtmosphere>
			<pressureQWGOutputCtpStraylightCorrFub>true
			</pressureQWGOutputCtpStraylightCorrFub>
			<pressureOutputP1Lise>true</pressureOutputP1Lise>
			<pressureOutputPSurfLise>true</pressureOutputPSurfLise>
			<pressureOutputP2Lise>true</pressureOutputP2Lise>
			<pressureOutputPScattLise>true</pressureOutputPScattLise>
			<cloudOutputBlueBand>true</cloudOutputBlueBand>
			<cloudOutputCloudProbability>true</cloudOutputCloudProbability>
			<cloudOutputCombinedCloud>true</cloudOutputCombinedCloud>
			<gaCopyRadiances>true</gaCopyRadiances>
			<gaCopyAnnotations>true</gaCopyAnnotations>
			<gaComputeFlagsOnly>true</gaComputeFlagsOnly>
			<ccCopyRadiances>true</ccCopyRadiances>
		</parameters>
	</node>
-->
</graph>
